LICENSE
README.md
setup.py
igv/__init__.py
igv/igv.py
igv/routes/__init__.py
igv/routes/basics.py
igv/routes/web.py
igv/static/static
igv/templates/custom.html
igv/templates/demo.html
igv/templates/templates
igv_flask.egg-info/PKG-INFO
igv_flask.egg-info/SOURCES.txt
igv_flask.egg-info/dependency_links.txt
igv_flask.egg-info/entry_points.txt
igv_flask.egg-info/not-zip-safe
igv_flask.egg-info/requires.txt
igv_flask.egg-info/top_level.txt