Metadata-Version: 2.1
Name: igv-flask
Version: 1.4
Summary: Flask webserver for rendering igv.js
Home-page: http://github.com/cumbof/igv-flask
Author: Fabio Cumbo
Author-email: fabio.cumbo@gmail.com
License: MIT
Download-URL: https://pypi.org/project/igv-flask/
Project-URL: Source, https://github.com/cumbof/igv-flask
Project-URL: Wiki, https://github.com/igvteam/igv.js/wiki
Keywords: bioinformatics,visualization
Platform: UNKNOWN
Classifier: Environment :: Console
Classifier: Intended Audience :: Science/Research
Classifier: License :: OSI Approved :: MIT License
Classifier: Natural Language :: English
Classifier: Programming Language :: Python :: 3
Classifier: Topic :: Scientific/Engineering :: Bio-Informatics
Requires-Python: >=3.6
